dummyfunction/__init__.py
dummyfunction/__main__.py
dummyfunction/core/__init__.py
dummyfunction/tests/__init__.py
dummyfunction/tests/test_1984.py
dummyfunction-1.0.4.dist-info/licenses/LICENSE.txt
dummyfunction-1.0.4.dist-info/METADATA
dummyfunction-1.0.4.dist-info/WHEEL
dummyfunction-1.0.4.dist-info/top_level.txt
dummyfunction-1.0.4.dist-info/RECORD
