Metadata-Version: 2.4
Name: dummyfunction
Version: 1.0.4
Summary: This project provides the dummy function.
Author-email: Johannes <johannes.programming@gmail.com>
License: The MIT License (MIT)
Project-URL: Download, https://pypi.org/project/dummyfunction/#files
Project-URL: Index, https://pypi.org/project/dummyfunction/
Project-URL: Source, https://github.com/johannes-programming/dummyfunction/
Project-URL: Website, https://dummyfunction.johannes-programming.online/
Classifier: Development Status :: 5 - Production/Stable
Classifier: Intended Audience :: Developers
Classifier: License :: OSI Approved :: MIT License
Classifier: Natural Language :: English
Classifier: Operating System :: OS Independent
Classifier: Programming Language :: Python
Classifier: Programming Language :: Python :: 3
Classifier: Programming Language :: Python :: 3 :: Only
Classifier: Typing :: Typed
Requires-Python: >=3.11
License-File: LICENSE.txt
Requires-Dist: click<9,>=8.2
Requires-Dist: preparse<2,>=0.1.6
Dynamic: license-file
